{"word": "abominable", "meanings": [{"pos": "s", "definition": "unequivocally detestable; ; ; ; - Edmund Burke", "synonyms": ["detestable", "execrable", "odious"], "examples": ["abominable treatment of prisoners", "detestable vices", "execrable crimes", "consequences odious to those you govern"]}, {"pos": "s", "definition": "exceptionally bad or displeasing", "synonyms": ["atrocious", "awful", "dreadful", "painful", "terrible", "unspeakable"], "examples": ["atrocious taste", "abominable workmanship", "an awful voice", "dreadful manners", "a painful performance", "terrible handwriting", "an unspeakable odor came sweeping into the room"]}]}