{"word": "about-face", "meanings": [{"pos": "n", "definition": "act of pivoting 180 degrees, especially in a military formation", "synonyms": ["about turn"], "examples": []}, {"pos": "n", "definition": "a major change in attitude or principle or point of view", "synonyms": ["volte-face", "reversal", "policy change"], "examples": ["an about-face on foreign policy"]}, {"pos": "v", "definition": "turn, usually 180 degrees", "synonyms": [], "examples": []}, {"pos": "v", "definition": "change one's mind and assume the opposite viewpoint", "synonyms": [], "examples": []}]}