{"word": "above", "meanings": [{"pos": "n", "definition": "an earlier section of a written text", "synonyms": [], "examples": ["for instructions refer to the above"]}, {"pos": "s", "definition": "appearing earlier in the same text", "synonyms": [], "examples": ["flaws in the above interpretation"]}, {"pos": "r", "definition": "at an earlier place", "synonyms": ["supra"], "examples": ["see above"]}, {"pos": "r", "definition": "in or to a place that is higher", "synonyms": ["higher up", "in a higher place", "to a higher place"], "examples": []}]}