{"word": "adorn", "meanings": [{"pos": "v", "definition": "make more attractive by adding ornament, colour, etc.", "synonyms": ["decorate", "grace", "ornament", "embellish", "beautify"], "examples": ["Decorate the room for the party", "beautify yourself for the special day"]}, {"pos": "v", "definition": "be beautiful to look at", "synonyms": ["deck", "decorate", "grace", "embellish", "beautify"], "examples": ["Flowers adorned the tables everywhere"]}, {"pos": "v", "definition": "furnish with power or authority; of kings or emperors", "synonyms": ["invest", "clothe"], "examples": []}]}