{"word": "aloft", "meanings": [{"pos": "r", "definition": "at or on or to the masthead or upper rigging of a ship", "synonyms": [], "examples": ["climbed aloft to unfurl the sail"]}, {"pos": "r", "definition": "upward", "synonyms": [], "examples": ["the good news sent her spirits aloft"]}, {"pos": "r", "definition": "at or to great height; high up in or into the air", "synonyms": [], "examples": ["eagles were soaring aloft", "dust is whirled aloft"]}, {"pos": "r", "definition": "in the higher atmosphere above the earth", "synonyms": [], "examples": ["weather conditions aloft are fine"]}]}