{"word": "being", "meanings": [{"pos": "n", "definition": "the state or fact of existing", "synonyms": ["beingness", "existence"], "examples": ["a point of view gradually coming into being", "laws in existence for centuries"]}, {"pos": "n", "definition": "a living thing that has (or can develop) the ability to act or function independently", "synonyms": ["organism"], "examples": []}, {"pos": "v", "definition": "have the quality of being; (copula, used with an adjective or a predicate noun)", "synonyms": ["be"], "examples": ["John is rich", "This is not a good answer"]}, {"pos": "v", "definition": "be identical to; be someone or something", "synonyms": ["be"], "examples": ["The president of the company is John Smith", "This is my house"]}, {"pos": "v", "definition": "occupy a certain position or area; be somewhere", "synonyms": ["be"], "examples": ["Where is my umbrella?", "The toolshed is in the back", "What is behind this behavior?"]}, {"pos": "v", "definition": "have an existence, be extant", "synonyms": ["exist", "be"], "examples": ["Is there a God?"]}, {"pos": "v", "definition": "happen, occur, take place", "synonyms": ["be"], "examples": ["I lost my wallet; this was during the visit to my parents' house", "There were two hundred people at his funeral", "There was a lot of noise in the kitchen"]}, {"pos": "v", "definition": "be identical or equivalent to", "synonyms": ["equal", "be"], "examples": ["One dollar equals 1,000 rubles these days!"]}, {"pos": "v", "definition": "form or compose", "synonyms": ["constitute", "represent", "make up", "comprise", "be"], "examples": ["This money is my only income", "The stone wall was the backdrop for the performance", "These constitute my entire belonging", "The children made up the chorus", "This sum represents my entire income for a year", "These few men comprise his entire army"]}, {"pos": "v", "definition": "work in a specific place, with a specific subject, or in a specific function", "synonyms": ["be", "follow"], "examples": ["He is a herpetologist", "She is our resident philosopher"]}, {"pos": "v", "definition": "represent, as of a character on stage", "synonyms": ["embody", "be", "personify"], "examples": ["Derek Jacobi was Hamlet"]}, {"pos": "v", "definition": "spend or use time", "synonyms": ["be"], "examples": ["I may be an hour"]}, {"pos": "v", "definition": "have life, be alive", "synonyms": ["be", "live"], "examples": ["Our great leader is no more", "My grandfather lived until the end of war"]}, {"pos": "v", "definition": "to remain unmolested, undisturbed, or uninterrupted -- used only in infinitive form", "synonyms": ["be"], "examples": ["let her be"]}, {"pos": "v", "definition": "be priced at", "synonyms": ["cost", "be"], "examples": ["These shoes cost $100"]}]}