{"word": "bootlicking", "meanings": [{"pos": "v", "definition": "try to gain favor by cringing or flattering", "synonyms": ["fawn", "toady", "truckle", "bootlick", "kowtow", "kotow", "suck up"], "examples": ["He is always kowtowing to his boss"]}, {"pos": "s", "definition": "attempting to win favor from influential people by flattery", "synonyms": ["fawning", "obsequious", "sycophantic", "toadyish"], "examples": []}, {"pos": "s", "definition": "attempting to win favor by flattery", "synonyms": ["fawning", "sycophantic", "toadyish"], "examples": []}]}