{"word": "call up", "meanings": [{"pos": "n", "definition": "an order to report for military duty", "synonyms": [], "examples": []}, {"pos": "v", "definition": "bring forward for consideration", "synonyms": ["bring forward"], "examples": ["The case was called up in court"]}, {"pos": "v", "definition": "get or try to get into communication (with someone) by telephone", "synonyms": ["call", "telephone", "phone", "ring"], "examples": ["I tried to call you all night", "Take two aspirin and call me in the morning"]}, {"pos": "v", "definition": "recall knowledge from memory; have a recollection", "synonyms": ["remember", "retrieve", "recall", "call back", "recollect", "think"], "examples": ["I can't remember saying any such thing", "I can't think what her last name was", "can you remember her phone number?", "Do you remember that he once loved you?", "call up memories"]}, {"pos": "v", "definition": "call to arms; of military personnel", "synonyms": ["mobilize", "mobilise", "rally"], "examples": []}]}