{"word": "clamor", "meanings": [{"pos": "n", "definition": "a loud harsh or strident noise", "synonyms": ["blare", "blaring", "cacophony", "din"], "examples": []}, {"pos": "n", "definition": "loud and persistent outcry from many people", "synonyms": ["clamoring", "clamour", "clamouring", "hue and cry"], "examples": ["he ignored the clamor of the crowd"]}, {"pos": "v", "definition": "make loud demands", "synonyms": ["clamour"], "examples": ["he clamored for justice and tolerance"]}, {"pos": "v", "definition": "utter or proclaim insistently and noisily", "synonyms": ["clamour"], "examples": ["The delegates clamored their disappointment"]}, {"pos": "v", "definition": "compel someone to do something by insistent clamoring", "synonyms": [], "examples": ["They clamored the mayor into building a new park"]}]}