{"word": "clay", "meanings": [{"pos": "n", "definition": "a very fine-grained soil that is plastic when moist but hard when fired", "synonyms": [], "examples": []}, {"pos": "n", "definition": "water soaked soil; soft wet earth", "synonyms": ["mud"], "examples": []}, {"pos": "n", "definition": "United States general who commanded United States forces in Europe from 1945 to 1949 and who oversaw the Berlin airlift (1897-1978)", "synonyms": ["Lucius Clay", "Lucius DuBignon Clay"], "examples": []}, {"pos": "n", "definition": "United States politician responsible for the Missouri Compromise between free and slave states (1777-1852)", "synonyms": ["Henry Clay", "the Great Compromiser"], "examples": []}, {"pos": "n", "definition": "the dead body of a human being", "synonyms": ["cadaver", "corpse", "stiff", "remains"], "examples": ["the cadaver was intended for dissection", "the end of the police search was the discovery of a corpse", "the murderer confessed that he threw the stiff in the river", "honor comes to bless the turf that wraps their clay"]}]}