{"word": "daily", "meanings": [{"pos": "n", "definition": "a newspaper that is published every day", "synonyms": [], "examples": []}, {"pos": "s", "definition": "of or belonging to or occurring every day", "synonyms": ["day-to-day", "day-by-day", "day-after-day"], "examples": ["daily routine", "a daily paper"]}, {"pos": "s", "definition": "appropriate for ordinary or routine occasions", "synonyms": ["casual", "everyday"], "examples": ["casual clothes", "everyday clothes"]}, {"pos": "r", "definition": "every day; without missing a day", "synonyms": [], "examples": ["he stops by daily"]}, {"pos": "r", "definition": "gradually and progressively", "synonyms": ["day by day"], "examples": ["his health weakened day by day"]}]}