{"word": "decision", "meanings": [{"pos": "n", "definition": "the act of making up your mind about something", "synonyms": ["determination", "conclusion"], "examples": ["the burden of decision was his", "he drew his conclusions quickly"]}, {"pos": "n", "definition": "a position or opinion or judgment reached after consideration", "synonyms": ["determination", "conclusion"], "examples": ["a decision unfavorable to the opposition", "his conclusion took the evidence into account", "satisfied with the panel's determination"]}, {"pos": "n", "definition": "(boxing) a victory won on points when no knockout has occurred", "synonyms": [], "examples": ["had little trouble in taking a unanimous decision over his opponent"]}, {"pos": "n", "definition": "the outcome of a game or contest", "synonyms": [], "examples": ["the team dropped three decisions in a row"]}, {"pos": "n", "definition": "the trait of resoluteness as evidenced by firmness of character or purpose", "synonyms": ["decisiveness"], "examples": ["a man of unusual decisiveness"]}]}