{"word": "expansive", "meanings": [{"pos": "a", "definition": "able or tending to expand or characterized by expansion", "synonyms": [], "examples": ["Expansive materials", "the expansive force of fire"]}, {"pos": "s", "definition": "of behavior that is impressive and ambitious in scale or scope", "synonyms": ["grand", "heroic"], "examples": ["an expansive lifestyle", "in the grand manner", "collecting on a grand scale", "heroic undertakings"]}, {"pos": "s", "definition": "marked by exaggerated feelings of euphoria and delusions of grandeur", "synonyms": [], "examples": []}, {"pos": "s", "definition": "friendly and open and willing to talk", "synonyms": ["talkative"], "examples": ["wine made the guest expansive"]}]}