{"word": "feeler", "meanings": [{"pos": "n", "definition": "one of a pair of mobile appendages on the head of e.g. insects and crustaceans; typically sensitive to touch and taste", "synonyms": ["antenna"], "examples": []}, {"pos": "n", "definition": "a tentative suggestion designed to elicit the reactions of others", "synonyms": ["overture", "advance", "approach"], "examples": ["she rejected his advances"]}, {"pos": "n", "definition": "sensitivity similar to that of a receptor organ", "synonyms": ["antenna"], "examples": ["he had a special antenna for public relations"]}, {"pos": "n", "definition": "slender tactile process on the jaws of a fish", "synonyms": ["barbel"], "examples": []}]}