{"word": "filipino", "meanings": [{"pos": "n", "definition": "a native or inhabitant of the Philippines", "synonyms": [], "examples": []}, {"pos": "n", "definition": "official language of the Philippines; based on Tagalog; draws its lexicon from other Philippine languages", "synonyms": ["Philippine"], "examples": []}, {"pos": "a", "definition": "of or relating to or characteristic of the Philippines or its people or customs", "synonyms": ["Philippine"], "examples": ["the Philippine President", "our Filipino cook"]}]}