{"word": "finishing", "meanings": [{"pos": "n", "definition": "a decorative texture or appearance of a surface (or the substance that gives it that appearance)", "synonyms": ["coating", "finish"], "examples": ["the boat had a metallic finish", "he applied a coat of a clear finish", "when the finish is too thin it is difficult to apply evenly"]}, {"pos": "n", "definition": "the act of finishing", "synonyms": ["finish"], "examples": ["his best finish in a major tournament was third", "the speaker's finishing was greeted with applause"]}, {"pos": "v", "definition": "come or bring to a finish or an end", "synonyms": ["complete", "finish"], "examples": ["He finished the dishes", "She completed the requirements for her Master's Degree", "The fastest runner finished the race in just over 2 hours; others finished in over 4 hours"]}, {"pos": "v", "definition": "finally be or do something", "synonyms": ["finish up", "land up", "fetch up", "end up", "wind up", "finish"], "examples": ["He ended up marrying his high school sweetheart", "he wound up being unemployed and living at home again"]}, {"pos": "v", "definition": "have an end, in a temporal, spatial, or quantitative sense; either spatial or metaphorical", "synonyms": ["end", "stop", "finish", "terminate", "cease"], "examples": ["the bronchioles terminate in a capillary bed", "Your rights stop where you infringe upon the rights of other", "My property ends by the bushes", "The symphony ends in a pianissimo"]}, {"pos": "v", "definition": "provide with a finish", "synonyms": ["finish"], "examples": ["The carpenter finished the table beautifully", "this shirt is not finished properly"]}, {"pos": "v", "definition": "finish eating all the food on one's plate or on the table", "synonyms": ["eat up", "finish", "polish off"], "examples": ["She polished off the remaining potatoes"]}, {"pos": "v", "definition": "cause to finish a relationship with somebody", "synonyms": ["finish"], "examples": ["That finished me with Mary"]}]}