{"word": "fused", "meanings": [{"pos": "v", "definition": "mix together different elements", "synonyms": ["blend", "flux", "mix", "conflate", "commingle", "immix", "fuse", "coalesce", "meld", "combine", "merge"], "examples": ["The colors blend well"]}, {"pos": "v", "definition": "become plastic or fluid or liquefied from heat", "synonyms": ["fuse"], "examples": ["The substances fused at a very high temperature"]}, {"pos": "v", "definition": "equip with a fuse; provide with a fuse", "synonyms": ["fuse"], "examples": []}, {"pos": "v", "definition": "make liquid or plastic by heating", "synonyms": ["fuse"], "examples": ["The storm fused the electric mains"]}, {"pos": "s", "definition": "joined together into a whole", "synonyms": ["amalgamate", "amalgamated", "coalesced", "consolidated"], "examples": ["United Industries", "the amalgamated colleges constituted a university", "a consolidated school"]}]}