{"word": "garnish", "meanings": [{"pos": "n", "definition": "something (such as parsley) added to a dish for flavor or decoration", "synonyms": [], "examples": []}, {"pos": "n", "definition": "any decoration added as a trimming or adornment", "synonyms": [], "examples": []}, {"pos": "v", "definition": "take a debtor's wages on legal orders, such as for child support", "synonyms": ["garnishee"], "examples": ["His employer garnished his wages in order to pay his debt"]}, {"pos": "v", "definition": "decorate (food), as with parsley or other ornamental foods", "synonyms": ["trim", "dress"], "examples": []}]}