{"word": "gimcrack", "meanings": [{"pos": "n", "definition": "ornamental objects of no great value", "synonyms": ["folderal", "falderol", "frill", "gimcrackery", "nonsense", "trumpery"], "examples": []}, {"pos": "s", "definition": "tastelessly showy", "synonyms": ["brassy", "cheap", "flash", "flashy", "garish", "gaudy", "loud", "meretricious", "tacky", "tatty", "tawdry", "trashy"], "examples": ["a flash car", "a flashy ring", "garish colors", "a gaudy costume", "loud sport shirts", "a meretricious yet stylish book", "tawdry ornaments"]}]}