{"word": "grab", "meanings": [{"pos": "n", "definition": "a mechanical device for gripping an object", "synonyms": [], "examples": []}, {"pos": "n", "definition": "the act of catching an object with the hands", "synonyms": ["catch", "snatch", "snap"], "examples": ["Mays made the catch with his back to the plate", "he made a grab for the ball before it landed", "Martin's snatch at the bridle failed and the horse raced away", "the infielder's snap and throw was a single motion"]}, {"pos": "v", "definition": "take hold of so as to seize or restrain or stop the motion of", "synonyms": ["catch", "take hold of"], "examples": ["Catch the ball!", "Grab the elevator door!"]}, {"pos": "v", "definition": "get hold of or seize quickly and easily", "synonyms": ["snap up", "snaffle"], "examples": ["I snapped up all the good buys during the garage sale"]}, {"pos": "v", "definition": "make a grasping or snatching motion with the hand", "synonyms": [], "examples": ["The passenger grabbed for the oxygen mask"]}, {"pos": "v", "definition": "obtain illegally or unscrupulously", "synonyms": [], "examples": ["Grab power"]}, {"pos": "v", "definition": "take or grasp suddenly", "synonyms": [], "examples": ["She grabbed the child's hand and ran out of the room"]}, {"pos": "v", "definition": "capture the attention or imagination of", "synonyms": ["seize"], "examples": ["This story will grab you", "The movie seized my imagination"]}]}