{"word": "grade", "meanings": [{"pos": "n", "definition": "a body of students who are taught together", "synonyms": ["class", "form", "course"], "examples": ["early morning classes are always sleepy"]}, {"pos": "n", "definition": "a relative position or degree of value in a graded group", "synonyms": ["level", "tier"], "examples": ["lumber of the highest grade"]}, {"pos": "n", "definition": "the gradient of a slope or road or other surface", "synonyms": [], "examples": ["the road had a steep grade"]}, {"pos": "n", "definition": "one-hundredth of a right angle", "synonyms": ["grad"], "examples": []}, {"pos": "n", "definition": "a degree of ablaut", "synonyms": ["gradation"], "examples": []}, {"pos": "n", "definition": "a number or letter indicating quality (especially of a student's performance)", "synonyms": ["mark", "score"], "examples": ["she made good marks in algebra", "grade A milk", "what was your score on your homework?"]}, {"pos": "n", "definition": "the height of the ground on which something stands", "synonyms": ["ground level"], "examples": ["the base of the tower was below grade"]}, {"pos": "n", "definition": "a position on a scale of intensity or amount or quality", "synonyms": ["degree", "level"], "examples": ["a moderate grade of intelligence", "a high level of care is required", "it is all a matter of degree"]}, {"pos": "n", "definition": "a variety of cattle produced by crossbreeding with a superior breed", "synonyms": [], "examples": []}, {"pos": "v", "definition": "assign a rank or rating to", "synonyms": ["rate", "rank", "range", "order", "place"], "examples": ["how would you rank these students?", "The restaurant is rated highly in the food guide"]}, {"pos": "v", "definition": "level to the right gradient", "synonyms": [], "examples": []}, {"pos": "v", "definition": "assign a grade or rank to, according to one's evaluation", "synonyms": ["score", "mark"], "examples": ["grade tests", "score the SAT essays", "mark homework"]}, {"pos": "v", "definition": "determine the grade of or assign a grade to", "synonyms": [], "examples": []}]}