{"word": "guy", "meanings": [{"pos": "n", "definition": "an informal term for a youth or man", "synonyms": ["cat", "hombre", "bozo"], "examples": ["a nice guy", "the guy's only doing it for some doll"]}, {"pos": "n", "definition": "an effigy of Guy Fawkes that is burned on a bonfire on Guy Fawkes Day", "synonyms": [], "examples": []}, {"pos": "n", "definition": "a cable, wire, or rope that is used to brace something (especially a tent)", "synonyms": ["guy cable", "guy wire", "guy rope"], "examples": []}, {"pos": "v", "definition": "subject to laughter or ridicule", "synonyms": ["ridicule", "roast", "blackguard", "laugh at", "jest at", "rib", "make fun", "poke fun"], "examples": ["The satirists ridiculed the plans for a new opera house", "The students poked fun at the inexperienced teacher", "His former students roasted the professor at his 60th birthday"]}, {"pos": "v", "definition": "steady or support with a guy wire or cable", "synonyms": [], "examples": ["The Italians guyed the Tower of Pisa to prevent it from collapsing"]}]}