{"word": "hard", "meanings": [{"pos": "a", "definition": "not easy; requiring great physical or mental effort to accomplish or comprehend or endure", "synonyms": ["difficult"], "examples": ["a difficult task", "nesting places on the cliffs are difficult of access", "difficult times", "why is it so hard for you to keep a secret?"]}, {"pos": "a", "definition": "dispassionate", "synonyms": [], "examples": ["took a hard look", "a hard bargainer"]}, {"pos": "a", "definition": "resisting weight or pressure", "synonyms": [], "examples": []}, {"pos": "s", "definition": "very strong or vigorous", "synonyms": ["knockout", "severe"], "examples": ["strong winds", "a hard left to the chin", "a knockout punch", "a severe blow"]}, {"pos": "s", "definition": "characterized by effort to the point of exhaustion; especially physical effort", "synonyms": ["arduous", "backbreaking", "grueling", "gruelling", "heavy", "laborious", "operose", "punishing", "toilsome"], "examples": ["worked their arduous way up the mining valley", "a grueling campaign", "hard labor", "heavy work", "heavy going", "spent many laborious hours on the project", "set a punishing pace"]}, {"pos": "a", "definition": "produced without vibration of the vocal cords", "synonyms": ["unvoiced", "voiceless", "surd"], "examples": ["unvoiced consonants such as `p' and `k' and `s'"]}, {"pos": "a", "definition": "(of light) transmitted directly from a pointed light source", "synonyms": ["concentrated"], "examples": []}, {"pos": "a", "definition": "(of speech sounds); produced with the back of the tongue raised toward or touching the velum", "synonyms": [], "examples": ["Russian distinguished between hard consonants and palatalized or soft consonants"]}, {"pos": "s", "definition": "given to excessive indulgence of bodily appetites especially for intoxicating liquors", "synonyms": ["intemperate", "heavy"], "examples": ["a hard drinker"]}, {"pos": "s", "definition": "being distilled rather than fermented; having a high alcoholic content", "synonyms": ["strong"], "examples": ["hard liquor"]}, {"pos": "s", "definition": "unfortunate or hard to bear", "synonyms": ["tough"], "examples": ["had hard luck", "a tough break"]}, {"pos": "s", "definition": "dried out", "synonyms": [], "examples": ["hard dry rolls left over from the day before"]}, {"pos": "r", "definition": "with effort or force or vigor", "synonyms": [], "examples": ["the team played hard", "worked hard all day", "pressed hard on the lever", "hit the ball hard", "slammed the door hard"]}, {"pos": "r", "definition": "with firmness", "synonyms": ["firmly"], "examples": ["held hard to the railing"]}, {"pos": "r", "definition": "earnestly or intently", "synonyms": [], "examples": ["thought hard about it", "stared hard at the accused"]}, {"pos": "r", "definition": "causing great damage or hardship", "synonyms": ["severely"], "examples": ["industries hit hard by the depression", "she was severely affected by the bank's failure"]}, {"pos": "r", "definition": "slowly and with difficulty", "synonyms": [], "examples": ["prejudices die hard"]}, {"pos": "r", "definition": "indulging excessively", "synonyms": ["heavily", "intemperately"], "examples": ["he drank heavily"]}, {"pos": "r", "definition": "into a solid condition", "synonyms": [], "examples": ["concrete that sets hard within a few hours"]}, {"pos": "r", "definition": "very near or close in space or time", "synonyms": [], "examples": ["it stands hard by the railroad tracks", "they were hard on his heels", "a strike followed hard upon the plant's opening"]}, {"pos": "r", "definition": "with pain or distress or bitterness", "synonyms": [], "examples": ["he took the rejection very hard"]}, {"pos": "r", "definition": "to the full extent possible; all the way", "synonyms": [], "examples": ["hard alee", "the ship went hard astern", "swung the wheel hard left"]}]}