{"word": "heave", "meanings": [{"pos": "n", "definition": "an upward movement (especially a rhythmical rising and falling)", "synonyms": ["heaving"], "examples": ["the heaving of waves on a rough sea"]}, {"pos": "n", "definition": "(geology) a horizontal dislocation", "synonyms": [], "examples": []}, {"pos": "n", "definition": "the act of lifting something with great effort", "synonyms": ["heaving"], "examples": []}, {"pos": "n", "definition": "an involuntary spasm of ineffectual vomiting", "synonyms": ["retch"], "examples": ["a bad case of the heaves"]}, {"pos": "n", "definition": "the act of raising something", "synonyms": ["lift", "raise"], "examples": ["he responded with a lift of his eyebrow", "fireman learn several different raises for getting ladders up"]}, {"pos": "n", "definition": "throwing something heavy (with great effort)", "synonyms": ["heaving"], "examples": ["he gave it a mighty heave", "he was not good at heaving passes"]}, {"pos": "v", "definition": "utter a sound, as with obvious effort", "synonyms": [], "examples": ["She heaved a deep sigh when she saw the list of things to do"]}, {"pos": "v", "definition": "throw with great effort", "synonyms": [], "examples": []}, {"pos": "v", "definition": "rise and move, as in waves or billows", "synonyms": ["billow", "surge"], "examples": ["The army surged forward"]}, {"pos": "v", "definition": "lift or elevate", "synonyms": ["heave up", "heft", "heft up"], "examples": []}, {"pos": "v", "definition": "move or cause to move in a specified way, direction, or position", "synonyms": [], "examples": ["The vessel hove into sight"]}, {"pos": "v", "definition": "breathe noisily, as when one is exhausted", "synonyms": ["pant", "puff", "gasp"], "examples": ["The runners reached the finish line, panting heavily"]}, {"pos": "v", "definition": "bend out of shape, as under pressure or from heat", "synonyms": ["buckle", "warp"], "examples": ["The highway buckled during the heat wave"]}, {"pos": "v", "definition": "make an unsuccessful effort to vomit; strain to vomit", "synonyms": ["gag", "retch"], "examples": []}]}