{"word": "identical", "meanings": [{"pos": "s", "definition": "exactly alike; incapable of being perceived as different", "synonyms": ["indistinguishable"], "examples": ["rows of identical houses", "cars identical except for their license plates", "they wore indistinguishable hats"]}, {"pos": "s", "definition": "being the exact same one; not any other:", "synonyms": ["selfsame", "very"], "examples": ["this is the identical room we stayed in before", "the themes of his stories are one and the same", "saw the selfsame quotation in two newspapers", "on this very spot", "the very thing he said yesterday", "the very man I want to see"]}, {"pos": "a", "definition": "(of twins) derived from a single egg or ovum", "synonyms": ["monovular"], "examples": ["identical twins are monovular"]}, {"pos": "s", "definition": "having properties with uniform values along all axes", "synonyms": [], "examples": []}, {"pos": "s", "definition": "coinciding exactly when superimposed", "synonyms": ["superposable"], "examples": ["identical triangles"]}]}