{"word": "incapacitated", "meanings": [{"pos": "v", "definition": "make unable to perform a certain action", "synonyms": ["disable", "disenable", "incapacitate"], "examples": ["disable this command on your computer"]}, {"pos": "v", "definition": "injure permanently", "synonyms": ["disable", "invalid", "incapacitate", "handicap"], "examples": ["He was disabled in a car accident"]}, {"pos": "s", "definition": "lacking in or deprived of strength or power", "synonyms": ["helpless"], "examples": ["lying ill and helpless", "helpless with laughter"]}]}