{"word": "indeterminate", "meanings": [{"pos": "a", "definition": "not precisely determined or established; not fixed or known in advance", "synonyms": ["undetermined"], "examples": ["of indeterminate age", "a zillion is a large indeterminate number", "an indeterminate point of law", "the influence of environment is indeterminate", "an indeterminate future"]}, {"pos": "a", "definition": "having a capacity for continuing to grow at the apex", "synonyms": [], "examples": ["an indeterminate stem"]}, {"pos": "s", "definition": "of uncertain or ambiguous nature", "synonyms": [], "examples": ["the equivocal (or indeterminate) objects painted by surrealists"]}, {"pos": "s", "definition": "not capable of being determined", "synonyms": [], "examples": ["the indeterminate number of plant species in the jungle"]}, {"pos": "s", "definition": "not leading to a definite ending or result", "synonyms": [], "examples": ["an indeterminate campaign"]}]}