{"word": "integral", "meanings": [{"pos": "n", "definition": "the result of a mathematical integration; F(x) is the integral of f(x) if dF/dx = f(x)", "synonyms": [], "examples": []}, {"pos": "s", "definition": "existing as an essential constituent or characteristic", "synonyms": ["built-in", "constitutional", "inbuilt", "inherent"], "examples": ["the Ptolemaic system with its built-in concept of periodicity", "a constitutional inability to tell the truth"]}, {"pos": "s", "definition": "constituting the undiminished entirety; lacking nothing essential especially not damaged; - Bacon", "synonyms": ["entire", "intact"], "examples": ["a local motion keepeth bodies integral", "was able to keep the collection entire during his lifetime", "fought to keep the union intact"]}, {"pos": "a", "definition": "of or denoted by an integer", "synonyms": [], "examples": []}]}