{"word": "jaded", "meanings": [{"pos": "v", "definition": "lose interest or become bored with something or somebody", "synonyms": ["tire", "pall", "weary", "fatigue", "jade"], "examples": ["I'm so tired of your mother and her complaints about my food"]}, {"pos": "v", "definition": "exhaust or get tired through overuse or great strain or stress", "synonyms": ["tire", "wear upon", "tire out", "wear", "weary", "jade", "wear out", "outwear", "wear down", "fag out", "fag", "fatigue"], "examples": ["We wore ourselves out on this hike"]}, {"pos": "s", "definition": "exhausted; - William Styron", "synonyms": ["wearied"], "examples": ["my father's words had left me jaded and depressed"]}, {"pos": "s", "definition": "dulled by surfeit", "synonyms": [], "examples": ["the amoral, jaded, bored upper classes"]}]}