{"word": "jejune", "meanings": [{"pos": "s", "definition": "lacking in nutritive value", "synonyms": ["insubstantial"], "examples": ["the jejune diets of the very poor"]}, {"pos": "s", "definition": "displaying or suggesting a lack of maturity", "synonyms": ["adolescent", "juvenile", "puerile"], "examples": ["adolescent insecurity", "jejune responses to our problems", "their behavior was juvenile", "puerile jokes"]}, {"pos": "s", "definition": "lacking interest or significance or impact", "synonyms": ["insipid"], "examples": ["an insipid personality", "jejune novel"]}]}