{"word": "lazy", "meanings": [{"pos": "s", "definition": "moving slowly and gently", "synonyms": [], "examples": ["up a lazy river", "lazy white clouds", "at a lazy pace"]}, {"pos": "s", "definition": "disinclined to work or exertion", "synonyms": ["faineant", "indolent", "otiose", "slothful", "work-shy"], "examples": ["faineant kings under whose rule the country languished", "an indolent hanger-on", "too lazy to wash the dishes", "shiftless idle youth", "slothful employees", "the unemployed are not necessarily work-shy"]}]}