{"word": "longer", "meanings": [{"pos": "n", "definition": "a person with a strong desire for something", "synonyms": ["thirster", "yearner"], "examples": ["a longer for money", "a thirster after blood", "a yearner for knowledge"]}, {"pos": "a", "definition": "primarily temporal sense; being or indicating a relatively great or greater than average duration or passage of time or a duration as specified", "synonyms": ["long"], "examples": ["a long life", "a long boring speech", "a long time", "a long friendship", "a long game", "long ago", "an hour long"]}, {"pos": "a", "definition": "primarily spatial sense; of relatively great or greater than average spatial extension or extension as specified", "synonyms": ["long"], "examples": ["a long road", "a long distance", "contained many long words", "ten miles long"]}, {"pos": "s", "definition": "of relatively great height; - Sherwood Anderson", "synonyms": ["long"], "examples": ["a race of long gaunt men", "looked out the long French windows"]}, {"pos": "a", "definition": "good at remembering", "synonyms": ["retentive", "recollective", "long", "tenacious"], "examples": ["a retentive mind", "tenacious memory"]}, {"pos": "a", "definition": "holding securities or commodities in expectation of a rise in prices", "synonyms": ["long"], "examples": ["is long on coffee", "a long position in gold"]}, {"pos": "a", "definition": "(of speech sounds or syllables) of relatively long duration", "synonyms": ["long"], "examples": ["the English vowel sounds in `bate', `beat', `bite', `boat', `boot' are long"]}, {"pos": "s", "definition": "involving substantial risk", "synonyms": ["long"], "examples": ["long odds"]}, {"pos": "s", "definition": "planning prudently for the future", "synonyms": ["farseeing", "farsighted", "foresighted", "foresightful", "prospicient", "long", "longsighted"], "examples": ["large goals that required farsighted policies", "took a long view of the geopolitical issues"]}, {"pos": "s", "definition": "having or being more than normal or necessary:", "synonyms": ["long"], "examples": ["long on brains", "in long supply"]}, {"pos": "r", "definition": "for more time", "synonyms": [], "examples": ["can I stay bit longer?"]}]}