{"word": "marginal", "meanings": [{"pos": "s", "definition": "at or constituting a border or edge", "synonyms": ["fringy"], "examples": ["the marginal strip of beach"]}, {"pos": "s", "definition": "of questionable or minimal quality", "synonyms": ["borderline"], "examples": ["borderline grades", "marginal writing ability"]}, {"pos": "s", "definition": "just barely adequate or within a lower limit", "synonyms": ["bare"], "examples": ["a bare majority", "a marginal victory"]}, {"pos": "s", "definition": "producing at a rate that barely covers production costs", "synonyms": [], "examples": ["marginal industries"]}]}