{"word": "milling", "meanings": [{"pos": "n", "definition": "corrugated edge of a coin", "synonyms": [], "examples": []}, {"pos": "v", "definition": "move about in a confused manner", "synonyms": ["mill", "mill about", "mill around"], "examples": []}, {"pos": "v", "definition": "grind with a mill", "synonyms": ["mill"], "examples": ["mill grain"]}, {"pos": "v", "definition": "produce a ridge around the edge of", "synonyms": ["mill"], "examples": ["mill a coin"]}, {"pos": "v", "definition": "roll out (metal) with a rolling machine", "synonyms": ["mill"], "examples": []}]}