{"word": "mute", "meanings": [{"pos": "n", "definition": "a deaf person who is unable to speak", "synonyms": ["deaf-mute", "deaf-and-dumb person"], "examples": []}, {"pos": "n", "definition": "a device used to soften the tone of a musical instrument", "synonyms": [], "examples": []}, {"pos": "v", "definition": "deaden (a sound or noise), especially by wrapping", "synonyms": ["muffle", "dull", "damp", "dampen", "tone down"], "examples": []}, {"pos": "s", "definition": "expressed without speech; ; ; - Emily Dickinson; ; ; - Thomas Wolfe", "synonyms": ["tongueless", "unspoken", "wordless"], "examples": ["a mute appeal", "a silent curse", "best grief is tongueless", "the words stopped at her lips unsounded", "unspoken grief", "choking exasperation and wordless shame"]}, {"pos": "s", "definition": "unable to speak because of hereditary deafness", "synonyms": ["dumb", "silent"], "examples": []}]}