{"word": "ottoman", "meanings": [{"pos": "n", "definition": "a Turk (especially a Turk who is a member of the tribe of Osman I)", "synonyms": ["Ottoman Turk", "Osmanli"], "examples": []}, {"pos": "n", "definition": "the Turkish dynasty that ruled the Ottoman Empire from the 13th century to its dissolution after World War I", "synonyms": ["Ottoman dynasty"], "examples": []}, {"pos": "n", "definition": "thick cushion used as a seat", "synonyms": ["pouf", "pouffe", "puff", "hassock"], "examples": []}, {"pos": "n", "definition": "a low seat or a stool to rest the feet of a seated person", "synonyms": ["footstool", "footrest", "tuffet"], "examples": []}, {"pos": "a", "definition": "of or relating to the Ottoman Empire or its people or its culture", "synonyms": [], "examples": []}]}