{"word": "outrageous", "meanings": [{"pos": "s", "definition": "grossly offensive to decency or morality; causing horror", "synonyms": ["hideous", "horrid", "horrific"], "examples": ["subjected to outrageous cruelty", "a hideous pattern of injustice", "horrific conditions in the mining industry"]}, {"pos": "s", "definition": "greatly exceeding bounds of reason or moderation", "synonyms": ["exorbitant", "extortionate", "steep", "unconscionable", "usurious"], "examples": ["exorbitant rent", "extortionate prices", "spends an outrageous amount on entertainment", "usurious interest rate", "unconscionable spending"]}]}