{"word": "passport", "meanings": [{"pos": "n", "definition": "any authorization to pass or go somewhere", "synonyms": ["pass"], "examples": ["the pass to visit had a strict time limit"]}, {"pos": "n", "definition": "a document issued by a country to a citizen allowing that person to travel abroad and re-enter the home country", "synonyms": [], "examples": []}, {"pos": "n", "definition": "any quality or characteristic that gains a person a favorable reception or acceptance or admission", "synonyms": ["recommendation"], "examples": ["her pleasant personality is already a recommendation", "his wealth was not a passport into the exclusive circles of society"]}]}