{"word": "propelling", "meanings": [{"pos": "v", "definition": "cause to move forward with force", "synonyms": ["propel", "impel"], "examples": ["Steam propels this ship"]}, {"pos": "v", "definition": "give an incentive for action", "synonyms": ["motivate", "actuate", "propel", "move", "prompt", "incite"], "examples": ["This moved me to sacrifice my career"]}, {"pos": "s", "definition": "tending to or capable of propelling", "synonyms": ["propellant", "propellent", "propulsive"], "examples": ["propellant fuel for submarines", "the faster a jet plane goes the greater its propulsive efficiency", "universities...the seats of propulsive thought"]}]}