{"word": "pull", "meanings": [{"pos": "n", "definition": "the act of pulling; applying force to move something toward or with you", "synonyms": ["pulling"], "examples": ["the pull up the hill had him breathing harder", "his strenuous pulling strained his back"]}, {"pos": "n", "definition": "the force used in pulling", "synonyms": [], "examples": ["the pull of the moon", "the pull of the current"]}, {"pos": "n", "definition": "special advantage or influence", "synonyms": ["clout"], "examples": ["the chairman's nephew has a lot of pull"]}, {"pos": "n", "definition": "a device used for pulling something", "synonyms": [], "examples": ["he grabbed the pull and opened the drawer"]}, {"pos": "n", "definition": "a sharp strain on muscles or ligaments", "synonyms": ["wrench", "twist"], "examples": ["the wrench to his knee occurred as he fell", "he was sidelined with a hamstring pull"]}, {"pos": "n", "definition": "a slow inhalation (as of tobacco smoke)", "synonyms": ["puff", "drag"], "examples": ["he took a puff on his pipe", "he took a drag on his cigarette and expelled the smoke slowly"]}, {"pos": "n", "definition": "a sustained effort", "synonyms": [], "examples": ["it was a long pull but we made it"]}, {"pos": "v", "definition": "cause to move by pulling", "synonyms": ["draw", "force"], "examples": ["draw a wagon", "pull a sled"]}, {"pos": "v", "definition": "direct toward itself or oneself by means of some psychological power or physical attributes", "synonyms": ["attract", "pull in", "draw", "draw in"], "examples": ["Her good looks attract the stares of many men", "The ad pulled in many potential customers", "This pianist pulls huge crowds", "The store owner was happy that the ad drew in many new customers"]}, {"pos": "v", "definition": "move into a certain direction", "synonyms": [], "examples": ["the car pulls to the right"]}, {"pos": "v", "definition": "apply force so as to cause motion towards the source of the motion", "synonyms": [], "examples": ["Pull the rope", "Pull the handle towards you", "pull the string gently", "pull the trigger of the gun", "pull your knees towards your chin"]}, {"pos": "v", "definition": "perform an act, usually with a negative connotation", "synonyms": ["perpetrate", "commit"], "examples": ["perpetrate a crime", "pull a bank robbery"]}, {"pos": "v", "definition": "bring, take, or pull out of a container or from under a cover", "synonyms": ["draw", "pull out", "get out", "take out"], "examples": ["draw a weapon", "pull out a gun", "The mugger pulled a knife on his victim"]}, {"pos": "v", "definition": "steer into a certain direction", "synonyms": [], "examples": ["pull one's horse to a stand", "Pull the car over"]}, {"pos": "v", "definition": "strain abnormally", "synonyms": ["overstretch"], "examples": ["I pulled a muscle in my leg when I jumped up", "The athlete pulled a tendon in the competition"]}, {"pos": "v", "definition": "cause to move in a certain direction by exerting a force upon, either physically or in an abstract sense", "synonyms": ["draw"], "examples": ["A declining dollar pulled down the export figures for the last quarter"]}, {"pos": "v", "definition": "operate when rowing a boat", "synonyms": [], "examples": ["pull the oars"]}, {"pos": "v", "definition": "rein in to keep from winning a race", "synonyms": [], "examples": ["pull a horse"]}, {"pos": "v", "definition": "tear or be torn violently", "synonyms": ["rend", "rip", "rive"], "examples": ["The curtain ripped from top to bottom", "pull the cooked chicken into strips"]}, {"pos": "v", "definition": "hit in the direction that the player is facing when carrying through the swing", "synonyms": [], "examples": ["pull the ball"]}, {"pos": "v", "definition": "strip of feathers", "synonyms": ["pluck", "tear", "deplume", "deplumate", "displume"], "examples": ["pull a chicken", "pluck the capon"]}, {"pos": "v", "definition": "remove, usually with some force or effort; also used in an abstract sense", "synonyms": ["extract", "pull out", "pull up", "take out", "draw out"], "examples": ["pull weeds", "extract a bad tooth", "take out a splinter", "extract information from the telegram"]}, {"pos": "v", "definition": "take sides with; align oneself with; show strong sympathy for", "synonyms": ["root for"], "examples": ["We all rooted for the home team", "I'm pulling for the underdog", "Are you siding with the defender of the title?"]}, {"pos": "v", "definition": "take away", "synonyms": [], "examples": ["pull the old soup cans from the supermarket shelf"]}]}