{"word": "ravenous", "meanings": [{"pos": "s", "definition": "extremely hungry", "synonyms": ["famished", "sharp-set", "starved", "esurient"], "examples": ["they were tired and famished for food and sleep", "a ravenous boy", "the family was starved and ragged", "fell into the esurient embrance of a predatory enemy"]}, {"pos": "s", "definition": "devouring or craving food in great quantities", "synonyms": ["edacious", "esurient", "rapacious", "ravening", "voracious", "wolfish"], "examples": ["edacious vultures", "a rapacious appetite", "ravenous as wolves", "voracious sharks"]}]}