{"word": "rut", "meanings": [{"pos": "n", "definition": "a groove or furrow (especially one in soft earth caused by wheels)", "synonyms": [], "examples": []}, {"pos": "n", "definition": "a settled and monotonous routine that is hard to escape", "synonyms": ["groove"], "examples": ["they fell into a conversational rut"]}, {"pos": "n", "definition": "applies to nonhuman mammals: a state or period of heightened sexual arousal and activity", "synonyms": ["estrus", "oestrus", "heat"], "examples": []}, {"pos": "v", "definition": "be in a state of sexual excitement; of male mammals", "synonyms": [], "examples": []}, {"pos": "v", "definition": "hollow out in the form of a furrow or groove", "synonyms": ["furrow", "groove"], "examples": ["furrow soil"]}]}