{"word": "santiago", "meanings": [{"pos": "n", "definition": "city in the northern Dominican Republic", "synonyms": ["Santiago de los Caballeros"], "examples": []}, {"pos": "n", "definition": "a port city in southeastern Cuba; industrial center", "synonyms": ["Santiago de Cuba"], "examples": []}, {"pos": "n", "definition": "the capital and largest city of Chile; located in central Chile; one of the largest cities in South America", "synonyms": ["Gran Santiago", "Santiago de Chile", "capital of Chile"], "examples": []}, {"pos": "n", "definition": "a naval battle in the Spanish-American War (1898); the United States fleet bottled up the Spanish ships in the harbor of Santiago de Cuba and destroyed them when they tried to escape", "synonyms": ["Santiago de Cuba"], "examples": []}]}