{"word": "seaward", "meanings": [{"pos": "n", "definition": "the direction toward the sea", "synonyms": [], "examples": []}, {"pos": "a", "definition": "(of winds) coming from the land", "synonyms": ["offshore"], "examples": ["offshore winds"]}, {"pos": "a", "definition": "(of winds) coming from the sea toward the land", "synonyms": ["inshore", "onshore", "shoreward"], "examples": ["an inshore breeze", "an onshore gale", "sheltered from seaward winds"]}, {"pos": "s", "definition": "directed or situated away from inland regions and toward the sea or coast", "synonyms": [], "examples": ["from the hill he took a seaward course", "on the seaward side of the road"]}, {"pos": "r", "definition": "in the direction of the sea", "synonyms": ["seawards", "asea"], "examples": ["the sailor looked seaward"]}]}