{"word": "smelling", "meanings": [{"pos": "n", "definition": "the act of perceiving the odor of something", "synonyms": ["smell"], "examples": []}, {"pos": "v", "definition": "inhale the odor of; perceive by the olfactory sense", "synonyms": ["smell"], "examples": []}, {"pos": "v", "definition": "emit an odor", "synonyms": ["smell"], "examples": ["The soup smells good"]}, {"pos": "v", "definition": "smell bad", "synonyms": ["smell"], "examples": ["He rarely washes, and he smells"]}, {"pos": "v", "definition": "have an element suggestive (of something)", "synonyms": ["smack", "reek", "smell"], "examples": ["his speeches smacked of racism", "this passage smells of plagiarism"]}, {"pos": "v", "definition": "become aware of not through the senses but instinctively", "synonyms": ["smell", "smell out", "sense"], "examples": ["I sense his hostility", "i smell trouble", "smell out corruption"]}, {"pos": "s", "definition": "(used with `of' or `with') noticeably odorous", "synonyms": ["redolent"], "examples": ["the hall was redolent of floor wax", "air redolent with the fumes of beer and whiskey"]}]}