{"word": "socializing", "meanings": [{"pos": "n", "definition": "the act of meeting for social purposes", "synonyms": ["socialization", "socialisation", "socialising"], "examples": ["there was too much socialization with the enlisted men"]}, {"pos": "v", "definition": "take part in social activities; interact with others", "synonyms": ["socialize", "socialise"], "examples": ["He never socializes with his colleagues", "The old man hates to socialize"]}, {"pos": "v", "definition": "train for a social environment", "synonyms": ["socialize", "socialise"], "examples": ["The children must be properly socialized"]}, {"pos": "v", "definition": "prepare for social life", "synonyms": ["socialize", "socialise"], "examples": ["Children have to be socialized in school"]}, {"pos": "v", "definition": "make conform to socialist ideas and philosophies", "synonyms": ["socialize", "socialise"], "examples": ["Health care should be socialized!"]}]}