{"word": "spider", "meanings": [{"pos": "n", "definition": "predatory arachnid with eight legs, two poison fangs, two feelers, and usually two silk-spinning organs at the back end of the body; they spin silk to make cocoons for eggs or traps for prey", "synonyms": [], "examples": []}, {"pos": "n", "definition": "a computer program that prowls the internet looking for publicly accessible resources that can be added to a database; the database can then be searched with a search engine", "synonyms": ["wanderer"], "examples": []}, {"pos": "n", "definition": "a skillet made of cast iron", "synonyms": [], "examples": []}]}