{"word": "squelched", "meanings": [{"pos": "v", "definition": "suppress or crush completely", "synonyms": ["squelch", "quell", "quench"], "examples": ["squelch any sign of dissent", "quench a rebellion"]}, {"pos": "v", "definition": "make a sucking sound", "synonyms": ["squelch"], "examples": []}, {"pos": "v", "definition": "walk through mud or mire", "synonyms": ["squelch", "squish", "splash", "splosh", "slosh", "slop"], "examples": ["We had to splosh across the wet meadow"]}, {"pos": "v", "definition": "to compress with violence, out of natural shape or condition", "synonyms": ["squash", "crush", "squelch", "mash", "squeeze"], "examples": ["crush an aluminum can", "squeeze a lemon"]}, {"pos": "s", "definition": "subdued or overcome", "synonyms": ["quelled", "quenched"], "examples": ["the quelled rebellion", "an uprising quenched almost before it started", "a squelched rumor"]}]}