{"word": "strong-arm", "meanings": [{"pos": "v", "definition": "handle roughly", "synonyms": [], "examples": ["He was strong-armed by the policemen"]}, {"pos": "v", "definition": "be bossy towards", "synonyms": ["bully", "browbeat", "bullyrag", "ballyrag", "boss around", "hector", "push around"], "examples": ["Her big brother always bullied her when she was young"]}, {"pos": "v", "definition": "use physical force against", "synonyms": [], "examples": ["They strong-armed me when I left the restaurant"]}, {"pos": "s", "definition": "impelled by physical force especially against resistance", "synonyms": ["forcible", "physical"], "examples": ["forcible entry", "a real cop would get physical", "strong-arm tactics"]}]}