{"word": "tacky", "meanings": [{"pos": "s", "definition": "(of a glutinous liquid such as paint) not completely dried and slightly sticky to the touch", "synonyms": [], "examples": ["tacky varnish"]}, {"pos": "s", "definition": "tastelessly showy", "synonyms": ["brassy", "cheap", "flash", "flashy", "garish", "gaudy", "gimcrack", "loud", "meretricious", "tatty", "tawdry", "trashy"], "examples": ["a flash car", "a flashy ring", "garish colors", "a gaudy costume", "loud sport shirts", "a meretricious yet stylish book", "tawdry ornaments"]}]}