{"word": "theology", "meanings": [{"pos": "n", "definition": "the rational and systematic study of religion and its influences and of the nature of religious truth", "synonyms": ["divinity"], "examples": []}, {"pos": "n", "definition": "a particular system or school of religious beliefs and teachings", "synonyms": ["theological system"], "examples": ["Jewish theology", "Roman Catholic theology"]}, {"pos": "n", "definition": "the learned profession acquired by specialized courses in religion (usually taught at a college or seminary)", "synonyms": [], "examples": ["he studied theology at Oxford"]}]}