{"word": "thinness", "meanings": [{"pos": "n", "definition": "relatively small dimension through an object as opposed to its length or width", "synonyms": ["tenuity", "slenderness"], "examples": ["the tenuity of a hair", "the thinness of a rope"]}, {"pos": "n", "definition": "the property of having little body fat", "synonyms": ["leanness", "spareness"], "examples": []}, {"pos": "n", "definition": "the property of being very narrow or thin", "synonyms": ["fineness"], "examples": ["he marvelled at the fineness of her hair"]}, {"pos": "n", "definition": "the property of being scanty or scattered; lacking denseness", "synonyms": ["sparseness", "spareness", "sparsity"], "examples": []}, {"pos": "n", "definition": "a consistency of low viscosity", "synonyms": [], "examples": ["he disliked the thinness of the soup"]}]}