{"word": "thong", "meanings": [{"pos": "n", "definition": "leather strip that forms the flexible part of a whip", "synonyms": ["lash"], "examples": []}, {"pos": "n", "definition": "underpants resembling a G-string; worn by women especially under very tight pants", "synonyms": [], "examples": ["she wore thongs in her quest for the callipygian ideal"]}, {"pos": "n", "definition": "a thin strip of leather; often used to lash things together", "synonyms": [], "examples": []}, {"pos": "n", "definition": "minimal clothing worn by stripteasers; a narrow strip of fabric that covers the pubic area, passes between the thighs, and is supported by a waistband", "synonyms": ["G-string"], "examples": []}, {"pos": "n", "definition": "a backless sandal held to the foot by a thong between the big toe and the second toe", "synonyms": ["flip-flop"], "examples": []}]}