{"word": "thunder", "meanings": [{"pos": "n", "definition": "a deep prolonged loud noise", "synonyms": ["boom", "roar", "roaring"], "examples": []}, {"pos": "n", "definition": "a booming or crashing noise caused by air expanding along the path of a bolt of lightning", "synonyms": [], "examples": []}, {"pos": "n", "definition": "street names for heroin", "synonyms": ["big H", "hell dust", "nose drops", "smack", "skag", "scag"], "examples": []}, {"pos": "v", "definition": "move fast, noisily, and heavily", "synonyms": [], "examples": ["The bus thundered down the road"]}, {"pos": "v", "definition": "utter words loudly and forcefully", "synonyms": ["roar"], "examples": ["`Get out of here,' he roared"]}, {"pos": "v", "definition": "be the case that thunder is being heard", "synonyms": ["boom"], "examples": ["Whenever it thunders, my dog crawls under the bed"]}, {"pos": "v", "definition": "to make or produce a loud noise", "synonyms": [], "examples": ["The river thundered below", "The engine roared as the driver pushed the car to full throttle"]}]}