{"word": "thwarting", "meanings": [{"pos": "n", "definition": "an act of hindering someone's plans or efforts", "synonyms": ["frustration", "foiling"], "examples": []}, {"pos": "v", "definition": "hinder or prevent (the efforts, plans, or desires) of", "synonyms": ["thwart", "queer", "spoil", "scotch", "foil", "cross", "frustrate", "baffle", "bilk"], "examples": ["What ultimately frustrated every challenger was Ruth's amazing September surge", "foil your opponent"]}, {"pos": "s", "definition": "preventing realization or attainment of a desire", "synonyms": ["frustrating", "frustrative"], "examples": []}]}