{"word": "trading", "meanings": [{"pos": "n", "definition": "buying or selling securities or commodities", "synonyms": [], "examples": []}, {"pos": "v", "definition": "engage in the trade of", "synonyms": ["trade", "merchandise"], "examples": ["he is merchandising telephone sets"]}, {"pos": "v", "definition": "turn in as payment or part payment for a purchase", "synonyms": ["trade", "trade in"], "examples": ["trade in an old car for a new one"]}, {"pos": "v", "definition": "be traded at a certain price or under certain conditions", "synonyms": ["trade"], "examples": ["The stock traded around $20 a share"]}, {"pos": "v", "definition": "exchange or give (something) in exchange for", "synonyms": ["trade", "swap", "swop", "switch"], "examples": []}, {"pos": "v", "definition": "do business; offer for sale as for one's livelihood", "synonyms": ["deal", "sell", "trade"], "examples": ["She deals in gold", "The brothers sell shoes"]}]}