{"word": "trickster", "meanings": [{"pos": "n", "definition": "someone who plays practical jokes on others", "synonyms": ["prankster", "cut-up", "tricker", "hoaxer", "practical joker"], "examples": []}, {"pos": "n", "definition": "someone who leads you to believe something that is not true", "synonyms": ["deceiver", "cheat", "cheater", "beguiler", "slicker"], "examples": []}, {"pos": "n", "definition": "a mischievous supernatural being found in the folklore of many primitive people; sometimes distinguished by prodigious biological drives and exaggerated bodily parts", "synonyms": [], "examples": []}]}