{"word": "underhand", "meanings": [{"pos": "a", "definition": "with hand brought forward and up from below shoulder level", "synonyms": ["underhanded", "underarm"], "examples": ["an underhand pitch", "an underhand stroke"]}, {"pos": "s", "definition": "marked by deception", "synonyms": ["sneaky", "underhanded"], "examples": ["achieved success in business only by underhand methods"]}, {"pos": "r", "definition": "slyly and secretly; - John Donne; - C.G.Bowers", "synonyms": ["underhandedly"], "examples": ["Mean revenge, committed underhand", "oldline aristocratic diplomats underhandedly undermined the attempt...to align Germany with the Western democracies"]}, {"pos": "r", "definition": "with the hand swung below shoulder level", "synonyms": ["underarm"], "examples": ["throwing a ball underarm"]}]}