{"word": "wager", "meanings": [{"pos": "n", "definition": "the act of gambling", "synonyms": ["bet"], "examples": ["he did it on a bet"]}, {"pos": "n", "definition": "the money risked on a gamble", "synonyms": ["stake", "stakes", "bet"], "examples": []}, {"pos": "v", "definition": "stake on the outcome of an issue", "synonyms": ["bet", "play"], "examples": ["I bet $100 on that new horse", "She played all her money on the dark horse"]}, {"pos": "v", "definition": "maintain with or as if with a bet", "synonyms": ["bet"], "examples": ["I bet she will be there!"]}]}