{"word": "weed", "meanings": [{"pos": "n", "definition": "any plant that crowds out cultivated plants", "synonyms": [], "examples": []}, {"pos": "n", "definition": "a black band worn by a man (on the arm or hat) as a sign of mourning", "synonyms": ["mourning band"], "examples": []}, {"pos": "n", "definition": "street names for marijuana", "synonyms": ["pot", "grass", "green goddess", "dope", "gage", "sess", "sens", "smoke", "skunk", "locoweed", "Mary Jane"], "examples": []}, {"pos": "v", "definition": "clear of weeds", "synonyms": [], "examples": ["weed the garden"]}]}