{"word": "yearly", "meanings": [{"pos": "n", "definition": "a reference book that is published regularly once every year", "synonyms": ["annual", "yearbook"], "examples": []}, {"pos": "s", "definition": "occurring or payable every year", "synonyms": ["annual"], "examples": ["an annual trip to Paris", "yearly medical examinations", "annual (or yearly) income"]}, {"pos": "r", "definition": "without missing a year", "synonyms": ["annually", "every year", "each year"], "examples": ["they travel to China annually"]}]}